pbf/__init__.py
pbf/config.py
pbf/setup.py
pbf/cli/__init__.py
pbf/controller/Cache.py
pbf/controller/Client.py
pbf/controller/Data.py
pbf/controller/Handler.py
pbf/controller/ListenerManager.py
pbf/controller/PluginsManager.py
pbf/controller/__init__.py
pbf/driver/Fastapi.py
pbf/driver/__init__.py
pbf/error/__init__.py
pbf/model/__init__.py
pbf/statement/AtStatement.py
pbf/statement/FaceStatement.py
pbf/statement/ImageStatement.py
pbf/statement/JsonStatement.py
pbf/statement/TextStatement.py
pbf/statement/XmlStatement.py
pbf/statement/__init__.py
pbf/utils/CQCode.py
pbf/utils/Config.py
pbf/utils/Logging.py
pbf/utils/Register.py
pbf/utils/__init__.py
PigBotFramework-5.0.12.dist-info/LICENSE
PigBotFramework-5.0.12.dist-info/METADATA
PigBotFramework-5.0.12.dist-info/WHEEL
PigBotFramework-5.0.12.dist-info/entry_points.txt
PigBotFramework-5.0.12.dist-info/top_level.txt
PigBotFramework-5.0.12.dist-info/RECORD
