Metadata-Version: 2.1
Name: PigBotFramework
Version: 5.0.12
Summary: PigBotFramework is a fast, easy-to-use, intelligent robot framework.
Home-page: https://github.com/PigBotFramework/next
Author: XzyStudio
Author-email: admin@xzynb.top
License: MIT
Project-URL: Documentation, https://pbfdocs.xzynb.top/
Project-URL: Source, https://github.com/PigBotFramework/next
Classifier: Development Status :: 5 - Production/Stable
Classifier: Operating System :: OS Independent
Classifier: License :: OSI Approved :: Apache Software License
Classifier: Programming Language :: Python
Classifier: Programming Language :: Python :: 3
Classifier: Programming Language :: Python :: 3.8
Classifier: Programming Language :: Python :: 3 :: Only
Classifier: Programming Language :: Python :: Implementation :: CPython
Classifier: Programming Language :: Python :: Implementation :: PyPy
Requires-Python: >=3.8.0
License-File: LICENSE
Requires-Dist: peewee ~=3.17.6
Requires-Dist: apscheduler ~=3.10.4
Requires-Dist: uvicorn ~=0.30.5
Requires-Dist: fastapi ~=0.112.0
Requires-Dist: requests ~=2.32.3
Requires-Dist: click ~=8.1.7
Requires-Dist: art ~=6.2
Requires-Dist: GitPython
